chromy/__init__.py
chromy/chromi.py
chromy/paths.py
chromy/structs.py
chromy-0.1.6.dist-info/licenses/LICENSE
chromy-0.1.6.dist-info/METADATA
chromy-0.1.6.dist-info/WHEEL
chromy-0.1.6.dist-info/top_level.txt
chromy-0.1.6.dist-info/RECORD
