Metadata-Version: 2.4
Name: chromy
Version: 0.1.6
Summary: 一个处理以 Chromium 为核心的浏览器用户数据的 Python 库
Author-email: Julian Freeman <freemanjulian372@gmail.com>
Project-URL: Homepage, https://github.com/JulianFreeman/chromy
Project-URL: Repository, https://github.com/JulianFreeman/chromy.git
Project-URL: Changelog, https://github.com/JulianFreeman/chromy/blob/main/CHANGELOG.md
Classifier: License :: OSI Approved :: GNU General Public License v3 (GPLv3)
Classifier: Operating System :: OS Independent
Classifier: Programming Language :: Python :: 3
Requires-Python: >=3.10
License-File: LICENSE
Requires-Dist: jnp3>=0.3.5
Dynamic: license-file
